llcsciencesdk/__init__.py
llcsciencesdk/api_types.py
llcsciencesdk/exceptions.py
llcsciencesdk/helpers.py
llcsciencesdk/llc_api.py
llcsciencesdk/parameter_mapping.py
llcsciencesdk/sample.py
llcsciencesdk/tests.py
llcsciencesdk/urls.py
llcsciencesdk-2.2.7.dist-info/LICENSE
llcsciencesdk-2.2.7.dist-info/WHEEL
llcsciencesdk-2.2.7.dist-info/METADATA
llcsciencesdk-2.2.7.dist-info/RECORD
