Metadata-Version: 2.1
Name: llcsciencesdk
Version: 2.2.7
Summary: A mini SDK for interacting with the LLC Science Admin
Author: Ariel Delgado
Author-email: a.delgado@landlifecompany.com
Classifier: License :: OSI Approved :: MIT License
